tgcrypto.cpython-312-arm-linux-gnueabihf.so
pytgcrypto-1.2.12.dist-info/COPYING
pytgcrypto-1.2.12.dist-info/COPYING.lesser
pytgcrypto-1.2.12.dist-info/METADATA
pytgcrypto-1.2.12.dist-info/NOTICE
pytgcrypto-1.2.12.dist-info/WHEEL
pytgcrypto-1.2.12.dist-info/top_level.txt
pytgcrypto-1.2.12.dist-info/RECORD
