Metadata-Version: 2.1
Name: pytgcrypto
Version: 1.2.12
Summary: Fast and Portable Cryptography Extension Library for Pyrogram
Home-page: https://github.com/TelegramPlayGround/pyrogram
Download-URL: https://github.com/TelegramPlayGround/pyrogram-tgcrypto/releases/latest
Author: SpEcHIDe
Author-email: pyrogram@iamidiotareyoutoo.com
License: LGPLv3+
Project-URL: Homepage, https://telegramplayground.github.io/pyrogram/
Project-URL: Tracker, https://github.com/TelegramPlayGround/pyrogram-tgcrypto/issues
Project-URL: Community, https://PyroTGFork.t.me/2
Project-URL: Source, https://github.com/TelegramPlayGround/pyrogram-tgcrypto
Project-URL: Documentation, https://telegramplayground.github.io/pyrogram/releases/changes-in-this-fork.html
Keywords: pyrogram telegram crypto cryptography encryption mtproto extension library aes
Classifier: Development Status :: 5 - Production/Stable
Classifier: Intended Audience :: Developers
Classifier: License :: OSI Approved :: GNU Lesser General Public License v3 or later (LGPLv3+)
Classifier: Operating System :: OS Independent
Classifier: Programming Language :: C
Classifier: Programming Language :: Python
Classifier: Programming Language :: Python :: 3
Classifier: Programming Language :: Python :: 3.7
Classifier: Programming Language :: Python :: 3.8
Classifier: Programming Language :: Python :: 3.9
Classifier: Programming Language :: Python :: 3.10
Classifier: Programming Language :: Python :: 3.11
Classifier: Programming Language :: Python :: 3.12
Classifier: Programming Language :: Python :: 3.13
Classifier: Programming Language :: Python :: 3.14
Classifier: Programming Language :: Python :: Implementation
Classifier: Programming Language :: Python :: Implementation :: CPython
Classifier: Programming Language :: Python :: Implementation :: PyPy
Classifier: Topic :: Security
Classifier: Topic :: Security :: Cryptography
Classifier: Topic :: Internet
Classifier: Topic :: Communications
Classifier: Topic :: Communications :: Chat
Classifier: Topic :: Software Development :: Libraries
Classifier: Topic :: Software Development :: Libraries :: Python Modules
Requires-Python: ~=3.7
License-File: COPYING
License-File: COPYING.lesser
License-File: NOTICE
